logprof.py
logprof-0.1.2.dist-info/METADATA
logprof-0.1.2.dist-info/WHEEL
logprof-0.1.2.dist-info/top_level.txt
logprof-0.1.2.dist-info/RECORD
