Metadata-Version: 2.4
Name: logprof
Version: 0.1.2
Summary: Simple logging profiler.
Author-email: Blair Azzopardi <blairuk@gmail.com>
License-Expression: MIT
Project-URL: repository, https://github.com/bsdz/logprof
Requires-Python: <4.0,>=3.10
Provides-Extra: dev
Requires-Dist: black<26.0.0,>=25.1.0; extra == "dev"
Requires-Dist: mypy<2.0.0,>=1.15.0; extra == "dev"
Requires-Dist: isort<7.0.0,>=6.0.1; extra == "dev"
Requires-Dist: docformatter<2.0.0,>=1.7.0; extra == "dev"
Requires-Dist: coverage<8.0.0,>=7.8.2; extra == "dev"
Requires-Dist: nox<2026.0.0,>=2025.5.1; extra == "dev"
Provides-Extra: test
Requires-Dist: pandas<3.0.0,>=2.2.3; extra == "test"
